sec_gemini/__init__.py
sec_gemini/constants.py
sec_gemini/enums.py
sec_gemini/file.py
sec_gemini/http.py
sec_gemini/logger.py
sec_gemini/secgemini.py
sec_gemini/session.py
sec_gemini/models/__init__.py
sec_gemini/models/attachment.py
sec_gemini/models/detach_file_request.py
sec_gemini/models/enums.py
sec_gemini/models/feedback.py
sec_gemini/models/message.py
sec_gemini/models/modelinfo.py
sec_gemini/models/opresult.py
sec_gemini/models/public.py
sec_gemini/models/session_request.py
sec_gemini/models/session_response.py
sec_gemini/models/usage.py
sec_gemini-1.1.5.dist-info/METADATA
sec_gemini-1.1.5.dist-info/WHEEL
sec_gemini-1.1.5.dist-info/top_level.txt
sec_gemini-1.1.5.dist-info/RECORD
