Metadata-Version: 2.4
Name: sec_gemini
Version: 1.1.5
Summary: Sec-Gemini Python SDK
Requires-Python: >=3.10
Requires-Dist: asyncio>=3.4.3
Requires-Dist: httpx>=0.28.1
Requires-Dist: magika>=0.6.2
Requires-Dist: openai>=1.59.7
Requires-Dist: orjson>=3.10.12
Requires-Dist: pydantic>=2.10.4
Requires-Dist: python-dotenv>=1.0.1
Requires-Dist: rich>=13.9.4
Requires-Dist: websockets>=14.1
